vpype_gcode/__init__.py
vpype_gcode/bundled_configs.toml
vpype_gcode/gwrite.py
vpype_gcode-0.13.0.dist-info/LICENSE
vpype_gcode-0.13.0.dist-info/METADATA
vpype_gcode-0.13.0.dist-info/WHEEL
vpype_gcode-0.13.0.dist-info/entry_points.txt
vpype_gcode-0.13.0.dist-info/top_level.txt
vpype_gcode-0.13.0.dist-info/RECORD
