Metadata-Version: 2.1
Name: vpype-gcode
Version: 0.13.0
Summary: vpype gcode plugin
Home-page: https://github.com/plottertools/vpype-gcode/
Author: Tatarize
Author-email: tatarize@gmail.com
Classifier: Programming Language :: Python :: 3.8
Classifier: Programming Language :: Python :: 3.9
Classifier: Programming Language :: Python :: 3.10
Classifier: Environment :: Console
Classifier: Topic :: Artistic Software
Classifier: Topic :: Multimedia :: Graphics
Classifier: License :: OSI Approved :: MIT License
Classifier: Operating System :: OS Independent
License-File: LICENSE
